<!DOCTYPE beans PUBLIC "-//SPRING//DTD BEAN//EN" "http://www.springframework.org/dtd/spring-beans.dtd">
<beans>
    <bean id="Insert-Contact-Facility_Prod"
          class="com.salesforce.dataloader.process.ProcessRunner"
          singleton="false">
        <description>Contact Insert job gets the Contact record updates from a CSV file and uploads them to salesforce using 'insert'.</description>
        <property name="name" value="Insert-Contact-Facility_Prod"/>
        <property name="configOverrideMap">
            <map>
                <entry key="sfdc.endpoint" value="https://imagineinstitute.my.salesforce.com"/> 
                <entry key="sfdc.username" value="calendar@501commons.org"/>
                <entry key="sfdc.password" value="41c54d6703a9a7e3ff5e10bdd8498552d9ac6476aae41e2b21c5d99229c554f33b25768df3adbdf7c6e1da27527fa4d791d6ec21f60b6bf8a0fa9c731d1c5080"/>
                <entry key="process.encryptionKeyFile" value="C:\repo\Salesforce-Importer-Private\Clients\II\DataLoader\key.txt"/>
                <entry key="sfdc.timeoutSecs" value="600"/>
                <entry key="sfdc.loadBatchSize" value="200"/>
                <entry key="sfdc.externalIdField" value="ii_Famlink_Id__c"/>
                <entry key="sfdc.entity" value="Contact"/>
                <entry key="process.operation" value="insert"/>
                <entry key="process.mappingFile" value="C:\repo\Salesforce-Importer-Private\Clients\II\Salesforce-Importer\Clients\II\DataLoader\Insert-Contact-Facility.sdl"/>
                <entry key="dataAccess.name" value="C:\repo\Salesforce-Importer-Private\Clients\II\Salesforce-Importer\Clients\II\Import\Insert-Contact-Facility.csv"/>
                <entry key="dataAccess.type" value="csvRead"/>
                <entry key="process.initialLastRunDate" value="2006-12-01T00:00:00.000-0800"/>
            </map>
        </property>
    </bean>
    <bean id="Insert-Contact-Subs_Prod"
          class="com.salesforce.dataloader.process.ProcessRunner"
          singleton="false">
        <description>Contact Insert job gets the Contact record updates from a CSV file and uploads them to salesforce using 'insert'.</description>
        <property name="name" value="Insert-Contact-Subs_Prod"/>
        <property name="configOverrideMap">
            <map>
                <entry key="sfdc.endpoint" value="https://imagineinstitute.my.salesforce.com"/> 
                <entry key="sfdc.username" value="calendar@501commons.org"/>
                <entry key="sfdc.password" value="41c54d6703a9a7e3ff5e10bdd8498552d9ac6476aae41e2b21c5d99229c554f33b25768df3adbdf7c6e1da27527fa4d791d6ec21f60b6bf8a0fa9c731d1c5080"/>
                <entry key="process.encryptionKeyFile" value="C:\repo\Salesforce-Importer-Private\Clients\II\DataLoader\key.txt"/>
                <entry key="sfdc.timeoutSecs" value="600"/>
                <entry key="sfdc.loadBatchSize" value="200"/>
                <entry key="sfdc.externalIdField" value="ii_Stars_Id__c"/>
                <entry key="sfdc.entity" value="Contact"/>
                <entry key="process.operation" value="insert"/>
                <entry key="process.mappingFile" value="C:\repo\Salesforce-Importer-Private\Clients\II\Salesforce-Importer\Clients\II\DataLoader\Insert-Contact-Subs.sdl"/>
                <entry key="dataAccess.name" value="C:\repo\Salesforce-Importer-Private\Clients\II\Salesforce-Importer\Clients\II\Import\Insert-Contact-Subs.csv"/>
                <entry key="dataAccess.type" value="csvRead"/>
                <entry key="process.initialLastRunDate" value="2006-12-01T00:00:00.000-0800"/>
            </map>
        </property>
    </bean>
    <bean id="Update-Contact-Facility_Prod"
          class="com.salesforce.dataloader.process.ProcessRunner"
          singleton="false">
        <description>Contact Update job gets the Contact record updates from a CSV file and uploads them to salesforce using 'update'.</description>
        <property name="name" value="Update-Contact-Facility_Prod"/>
        <property name="configOverrideMap">
            <map>
                <entry key="sfdc.endpoint" value="https://imagineinstitute.my.salesforce.com"/> 
                <entry key="sfdc.username" value="calendar@501commons.org"/>
                <entry key="sfdc.password" value="41c54d6703a9a7e3ff5e10bdd8498552d9ac6476aae41e2b21c5d99229c554f33b25768df3adbdf7c6e1da27527fa4d791d6ec21f60b6bf8a0fa9c731d1c5080"/>
                <entry key="process.encryptionKeyFile" value="C:\repo\Salesforce-Importer-Private\Clients\II\DataLoader\key.txt"/>
                <entry key="sfdc.timeoutSecs" value="600"/>
                <entry key="sfdc.loadBatchSize" value="200"/>
                <entry key="sfdc.externalIdField" value="Id"/>
                <entry key="sfdc.entity" value="Contact"/>
                <entry key="process.operation" value="update"/>
                <entry key="process.mappingFile" value="C:\repo\Salesforce-Importer-Private\Clients\II\Salesforce-Importer\Clients\II\DataLoader\Update-Contact-Facility.sdl"/>
                <entry key="dataAccess.name" value="C:\repo\Salesforce-Importer-Private\Clients\II\Salesforce-Importer\Clients\II\Import\Update-Contact-Facility.csv"/>
                <entry key="dataAccess.type" value="csvRead"/>
                <entry key="process.initialLastRunDate" value="2006-12-01T00:00:00.000-0800"/>
            </map>
        </property>
    </bean>
    <bean id="Update-Contact-Subs_Prod"
          class="com.salesforce.dataloader.process.ProcessRunner"
          singleton="false">
        <description>Contact Update job gets the Contact record updates from a CSV file and uploads them to salesforce using 'update'.</description>
        <property name="name" value="Update-Contact-Subs_Prod"/>
        <property name="configOverrideMap">
            <map>
                <entry key="sfdc.endpoint" value="https://imagineinstitute.my.salesforce.com"/> 
                <entry key="sfdc.username" value="calendar@501commons.org"/>
                <entry key="sfdc.password" value="41c54d6703a9a7e3ff5e10bdd8498552d9ac6476aae41e2b21c5d99229c554f33b25768df3adbdf7c6e1da27527fa4d791d6ec21f60b6bf8a0fa9c731d1c5080"/>
                <entry key="process.encryptionKeyFile" value="C:\repo\Salesforce-Importer-Private\Clients\II\DataLoader\key.txt"/>
                <entry key="sfdc.timeoutSecs" value="600"/>
                <entry key="sfdc.loadBatchSize" value="200"/>
                <entry key="sfdc.externalIdField" value="Id"/>
                <entry key="sfdc.entity" value="Contact"/>
                <entry key="process.operation" value="update"/>
                <entry key="process.mappingFile" value="C:\repo\Salesforce-Importer-Private\Clients\II\Salesforce-Importer\Clients\II\DataLoader\Update-Contact-Subs.sdl"/>
                <entry key="dataAccess.name" value="C:\repo\Salesforce-Importer-Private\Clients\II\Salesforce-Importer\Clients\II\Import\Update-Contact-Subs.csv"/>
                <entry key="dataAccess.type" value="csvRead"/>
                <entry key="process.initialLastRunDate" value="2006-12-01T00:00:00.000-0800"/>
            </map>
        </property>
    </bean>    
    <bean id="Update-Contact-Facility-NotApp_Prod"
          class="com.salesforce.dataloader.process.ProcessRunner"
          singleton="false">
        <description>Contact Update job gets the Contact record updates from a CSV file and uploads them to salesforce using 'update'.</description>
        <property name="name" value="Update-Contact-Facility-NotApp_Prod"/>
        <property name="configOverrideMap">
            <map>
                <entry key="sfdc.endpoint" value="https://imagineinstitute.my.salesforce.com"/> 
                <entry key="sfdc.username" value="calendar@501commons.org"/>
                <entry key="sfdc.password" value="41c54d6703a9a7e3ff5e10bdd8498552d9ac6476aae41e2b21c5d99229c554f33b25768df3adbdf7c6e1da27527fa4d791d6ec21f60b6bf8a0fa9c731d1c5080"/>
                <entry key="process.encryptionKeyFile" value="C:\repo\Salesforce-Importer-Private\Clients\II\DataLoader\key.txt"/>
                <entry key="sfdc.timeoutSecs" value="600"/>
                <entry key="sfdc.loadBatchSize" value="200"/>
                <entry key="sfdc.externalIdField" value="Id"/>
                <entry key="sfdc.entity" value="Contact"/>
                <entry key="process.operation" value="update"/>
                <entry key="process.mappingFile" value="C:\repo\Salesforce-Importer-Private\Clients\II\Salesforce-Importer\Clients\II\DataLoader\Update-Contact-Facility-NotApp.sdl"/>
                <entry key="dataAccess.name" value="C:\repo\Salesforce-Importer-Private\Clients\II\Salesforce-Importer\Clients\II\Import\Update-Contact-Facility-NotApp.csv"/>
                <entry key="dataAccess.type" value="csvRead"/>
                <entry key="process.initialLastRunDate" value="2006-12-01T00:00:00.000-0800"/>
            </map>
        </property>
    </bean>
    <bean id="Update-Contact-Subs-NotApp_Prod"
          class="com.salesforce.dataloader.process.ProcessRunner"
          singleton="false">
        <description>Contact Update job gets the Contact record updates from a CSV file and uploads them to salesforce using 'update'.</description>
        <property name="name" value="Update-Contact-Subs-NotApp_Prod"/>
        <property name="configOverrideMap">
            <map>
                <entry key="sfdc.endpoint" value="https://imagineinstitute.my.salesforce.com"/> 
                <entry key="sfdc.username" value="calendar@501commons.org"/>
                <entry key="sfdc.password" value="41c54d6703a9a7e3ff5e10bdd8498552d9ac6476aae41e2b21c5d99229c554f33b25768df3adbdf7c6e1da27527fa4d791d6ec21f60b6bf8a0fa9c731d1c5080"/>
                <entry key="process.encryptionKeyFile" value="C:\repo\Salesforce-Importer-Private\Clients\II\DataLoader\key.txt"/>
                <entry key="sfdc.timeoutSecs" value="600"/>
                <entry key="sfdc.loadBatchSize" value="200"/>
                <entry key="sfdc.externalIdField" value="Id"/>
                <entry key="sfdc.entity" value="Contact"/>
                <entry key="process.operation" value="update"/>
                <entry key="process.mappingFile" value="C:\repo\Salesforce-Importer-Private\Clients\II\Salesforce-Importer\Clients\II\DataLoader\Update-Contact-Subs-NotApp.sdl"/>
                <entry key="dataAccess.name" value="C:\repo\Salesforce-Importer-Private\Clients\II\Salesforce-Importer\Clients\II\Import\Update-Contact-Subs-NotApp.csv"/>
                <entry key="dataAccess.type" value="csvRead"/>
                <entry key="process.initialLastRunDate" value="2006-12-01T00:00:00.000-0800"/>
            </map>
        </property>
    </bean>
    <bean id="Update-AM-Campus-User_Prod"
          class="com.salesforce.dataloader.process.ProcessRunner"
          singleton="false">
        <description>Contact Update job gets the Contact record updates from a CSV file and uploads them to salesforce using 'update'.</description>
        <property name="name" value="Update-AM-Campus-User_Prod"/>
        <property name="configOverrideMap">
            <map>
                <entry key="sfdc.endpoint" value="https://imagineinstitute.my.salesforce.com"/> 
                <entry key="sfdc.username" value="calendar@501commons.org"/>
                <entry key="sfdc.password" value="41c54d6703a9a7e3ff5e10bdd8498552d9ac6476aae41e2b21c5d99229c554f33b25768df3adbdf7c6e1da27527fa4d791d6ec21f60b6bf8a0fa9c731d1c5080"/>
                <entry key="process.encryptionKeyFile" value="C:\repo\Salesforce-Importer-Private\Clients\II\DataLoader\key.txt"/>
                <entry key="sfdc.timeoutSecs" value="600"/>
                <entry key="sfdc.loadBatchSize" value="200"/>
                <entry key="sfdc.externalIdField" value="Id"/>
                <entry key="sfdc.entity" value="Contact"/>
                <entry key="process.operation" value="update"/>
                <entry key="process.mappingFile" value="C:\repo\Salesforce-Importer-Private\Clients\II\Salesforce-Importer\Clients\II\DataLoader\Update-AM-Campus-User.sdl"/>
                <entry key="dataAccess.name" value="C:\repo\Salesforce-Importer-Private\Clients\II\Salesforce-Importer\Clients\II\Import\Update-AM-Campus-User.csv"/>
                <entry key="dataAccess.type" value="csvRead"/>
                <entry key="process.initialLastRunDate" value="2006-12-01T00:00:00.000-0800"/>
            </map>
        </property>
    </bean>
    <bean id="Update-AM-Facility_Prod"
          class="com.salesforce.dataloader.process.ProcessRunner"
          singleton="false">
        <description>Contact Update job gets the Contact record updates from a CSV file and uploads them to salesforce using 'update'.</description>
        <property name="name" value="Update-AM-Facility_Prod"/>
        <property name="configOverrideMap">
            <map>
                <entry key="sfdc.endpoint" value="https://imagineinstitute.my.salesforce.com"/> 
                <entry key="sfdc.username" value="calendar@501commons.org"/>
                <entry key="sfdc.password" value="41c54d6703a9a7e3ff5e10bdd8498552d9ac6476aae41e2b21c5d99229c554f33b25768df3adbdf7c6e1da27527fa4d791d6ec21f60b6bf8a0fa9c731d1c5080"/>
                <entry key="process.encryptionKeyFile" value="C:\repo\Salesforce-Importer-Private\Clients\II\DataLoader\key.txt"/>
                <entry key="sfdc.timeoutSecs" value="600"/>
                <entry key="sfdc.loadBatchSize" value="200"/>
                <entry key="sfdc.externalIdField" value="Id"/>
                <entry key="sfdc.entity" value="Contact"/>
                <entry key="process.operation" value="update"/>
                <entry key="process.mappingFile" value="C:\repo\Salesforce-Importer-Private\Clients\II\Salesforce-Importer\Clients\II\DataLoader\Update-AM-Facility.sdl"/>
                <entry key="dataAccess.name" value="C:\repo\Salesforce-Importer-Private\Clients\II\Salesforce-Importer\Clients\II\Import\Update-AM-Facility.csv"/>
                <entry key="dataAccess.type" value="csvRead"/>
                <entry key="process.initialLastRunDate" value="2006-12-01T00:00:00.000-0800"/>
            </map>
        </property>
    </bean>
    <bean id="Update-AM-Subs_Prod"
          class="com.salesforce.dataloader.process.ProcessRunner"
          singleton="false">
        <description>Contact Update job gets the Contact record updates from a CSV file and uploads them to salesforce using 'update'.</description>
        <property name="name" value="Update-AM-Subs_Prod"/>
        <property name="configOverrideMap">
            <map>
                <entry key="sfdc.endpoint" value="https://imagineinstitute.my.salesforce.com"/> 
                <entry key="sfdc.username" value="calendar@501commons.org"/>
                <entry key="sfdc.password" value="41c54d6703a9a7e3ff5e10bdd8498552d9ac6476aae41e2b21c5d99229c554f33b25768df3adbdf7c6e1da27527fa4d791d6ec21f60b6bf8a0fa9c731d1c5080"/>
                <entry key="process.encryptionKeyFile" value="C:\repo\Salesforce-Importer-Private\Clients\II\DataLoader\key.txt"/>
                <entry key="sfdc.timeoutSecs" value="600"/>
                <entry key="sfdc.loadBatchSize" value="200"/>
                <entry key="sfdc.externalIdField" value="Id"/>
                <entry key="sfdc.entity" value="Contact"/>
                <entry key="process.operation" value="update"/>
                <entry key="process.mappingFile" value="C:\repo\Salesforce-Importer-Private\Clients\II\Salesforce-Importer\Clients\II\DataLoader\Update-AM-Subs.sdl"/>
                <entry key="dataAccess.name" value="C:\repo\Salesforce-Importer-Private\Clients\II\Salesforce-Importer\Clients\II\Import\Update-AM-Subs.csv"/>
                <entry key="dataAccess.type" value="csvRead"/>
                <entry key="process.initialLastRunDate" value="2006-12-01T00:00:00.000-0800"/>
            </map>
        </property>
    </bean>
    <bean id="Insert-Contact-Training_Prod"
          class="com.salesforce.dataloader.process.ProcessRunner"
          singleton="false">
        <description>Contact Insert job gets the Contact record updates from a CSV file and uploads them to salesforce using 'insert'.</description>
        <property name="name" value="Insert-Contact-Training_Prod"/>
        <property name="configOverrideMap">
            <map>
                <entry key="sfdc.endpoint" value="https://imagineinstitute.my.salesforce.com"/> 
                <entry key="sfdc.username" value="calendar@501commons.org"/>
                <entry key="sfdc.password" value="41c54d6703a9a7e3ff5e10bdd8498552d9ac6476aae41e2b21c5d99229c554f33b25768df3adbdf7c6e1da27527fa4d791d6ec21f60b6bf8a0fa9c731d1c5080"/>
                <entry key="process.encryptionKeyFile" value="C:\repo\Salesforce-Importer-Private\Clients\II\DataLoader\key.txt"/>
                <entry key="sfdc.timeoutSecs" value="600"/>
                <entry key="sfdc.loadBatchSize" value="200"/>
                <entry key="sfdc.externalIdField" value="ii_Member_Id__c"/>
                <entry key="sfdc.entity" value="Contact"/>
                <entry key="process.operation" value="insert"/>
                <entry key="process.mappingFile" value="C:\repo\Salesforce-Importer-Private\Clients\II\Salesforce-Importer\Clients\II\DataLoader\Insert-Contact-Training.sdl"/>
                <entry key="dataAccess.name" value="C:\repo\Salesforce-Importer-Private\Clients\II\Salesforce-Importer\Clients\II\Import\Insert-Contact-Training.csv"/>
                <entry key="dataAccess.type" value="csvRead"/>
                <entry key="process.initialLastRunDate" value="2006-12-01T00:00:00.000-0800"/>
            </map>
        </property>
    </bean>
    <bean id="Update-Contact-Training_Prod"
          class="com.salesforce.dataloader.process.ProcessRunner"
          singleton="false">
        <description>Contact Update job gets the Contact record updates from a CSV file and uploads them to salesforce using 'update'.</description>
        <property name="name" value="Update-Contact-Training_Prod"/>
        <property name="configOverrideMap">
            <map>
                <entry key="sfdc.endpoint" value="https://imagineinstitute.my.salesforce.com"/> 
                <entry key="sfdc.username" value="calendar@501commons.org"/>
                <entry key="sfdc.password" value="41c54d6703a9a7e3ff5e10bdd8498552d9ac6476aae41e2b21c5d99229c554f33b25768df3adbdf7c6e1da27527fa4d791d6ec21f60b6bf8a0fa9c731d1c5080"/>
                <entry key="process.encryptionKeyFile" value="C:\repo\Salesforce-Importer-Private\Clients\II\DataLoader\key.txt"/>
                <entry key="sfdc.timeoutSecs" value="600"/>
                <entry key="sfdc.loadBatchSize" value="200"/>
                <entry key="sfdc.externalIdField" value="Id"/>
                <entry key="sfdc.entity" value="Contact"/>
                <entry key="process.operation" value="update"/>
                <entry key="process.mappingFile" value="C:\repo\Salesforce-Importer-Private\Clients\II\Salesforce-Importer\Clients\II\DataLoader\Update-Contact-Training.sdl"/>
                <entry key="dataAccess.name" value="C:\repo\Salesforce-Importer-Private\Clients\II\Salesforce-Importer\Clients\II\Import\Update-Contact-Training.csv"/>
                <entry key="dataAccess.type" value="csvRead"/>
                <entry key="process.initialLastRunDate" value="2006-12-01T00:00:00.000-0800"/>
            </map>
        </property>
    </bean>
    <bean id="Update-Training-OutOfUnit_Prod"
          class="com.salesforce.dataloader.process.ProcessRunner"
          singleton="false">
        <description>Contact Update job gets the Contact record updates from a CSV file and uploads them to salesforce using 'update'.</description>
        <property name="name" value="Update-Traininig-OutOfUnit_Prod"/>
        <property name="configOverrideMap">
            <map>
                <entry key="sfdc.endpoint" value="https://imagineinstitute.my.salesforce.com"/> 
                <entry key="sfdc.username" value="calendar@501commons.org"/>
                <entry key="sfdc.password" value="41c54d6703a9a7e3ff5e10bdd8498552d9ac6476aae41e2b21c5d99229c554f33b25768df3adbdf7c6e1da27527fa4d791d6ec21f60b6bf8a0fa9c731d1c5080"/>
                <entry key="process.encryptionKeyFile" value="C:\repo\Salesforce-Importer-Private\Clients\II\DataLoader\key.txt"/>
                <entry key="sfdc.timeoutSecs" value="600"/>
                <entry key="sfdc.loadBatchSize" value="200"/>
                <entry key="sfdc.externalIdField" value="Id"/>
                <entry key="sfdc.entity" value="Contact"/>
                <entry key="process.operation" value="update"/>
                <entry key="process.mappingFile" value="C:\repo\Salesforce-Importer-Private\Clients\II\Salesforce-Importer\Clients\II\DataLoader\Update-Training-OutOfUnit.sdl"/>
                <entry key="dataAccess.name" value="C:\repo\Salesforce-Importer-Private\Clients\II\Salesforce-Importer\Clients\II\Import\Update-Training-OutOfUnit.csv"/>
                <entry key="dataAccess.type" value="csvRead"/>
                <entry key="process.initialLastRunDate" value="2006-12-01T00:00:00.000-0800"/>
            </map>
        </property>
    </bean>
    <bean id="Insert-Contact-Facility_Sandbox"
          class="com.salesforce.dataloader.process.ProcessRunner"
          singleton="false">
        <description>Contact Insert job gets the Contact record updates from a CSV file and uploads them to salesforce using 'insert'.</description>
        <property name="name" value="Insert-Contact-Facility_Sandbox"/>
        <property name="configOverrideMap">
            <map>
                <entry key="sfdc.endpoint" value="https://test.salesforce.com"/> 
                <entry key="sfdc.username" value="calendar@501commons.org.master"/>
                <entry key="sfdc.password" value="c347e0598ea8455126755d47471397f251536bee9164f04783fea47428559fbabb71d46e60e6a078f86fa2d30ac340ff8e64c0ca66648917a8a949e7533de9ab"/>
                <entry key="process.encryptionKeyFile" value="C:\repo\Salesforce-Importer-Private\Clients\II\DataLoader\key.txt"/>
                <entry key="sfdc.timeoutSecs" value="600"/>
                <entry key="sfdc.loadBatchSize" value="200"/>
                <entry key="sfdc.externalIdField" value="ii_Famlink_Id__c"/>
                <entry key="sfdc.entity" value="Contact"/>
                <entry key="process.operation" value="insert"/>
                <entry key="process.mappingFile" value="C:\repo\Salesforce-Importer-Private\Clients\II\Salesforce-Importer\Clients\II\DataLoader\Insert-Contact-Facility.sdl"/>
                <entry key="dataAccess.name" value="C:\repo\Salesforce-Importer-Private\Clients\II\Salesforce-Importer\Clients\II\Import\Insert-Contact-Facility.csv"/>
                <entry key="dataAccess.type" value="csvRead"/>
                <entry key="process.initialLastRunDate" value="2006-12-01T00:00:00.000-0800"/>
            </map>
        </property>
    </bean>
    <bean id="Insert-Contact-Subs_Sandbox"
          class="com.salesforce.dataloader.process.ProcessRunner"
          singleton="false">
        <description>Contact Insert job gets the Contact record updates from a CSV file and uploads them to salesforce using 'insert'.</description>
        <property name="name" value="Insert-Contact-Subs_Sandbox"/>
        <property name="configOverrideMap">
            <map>
                <entry key="sfdc.endpoint" value="https://test.salesforce.com"/> 
                <entry key="sfdc.username" value="calendar@501commons.org.master"/>
                <entry key="sfdc.password" value="c347e0598ea8455126755d47471397f251536bee9164f04783fea47428559fbabb71d46e60e6a078f86fa2d30ac340ff8e64c0ca66648917a8a949e7533de9ab"/>
                <entry key="process.encryptionKeyFile" value="C:\repo\Salesforce-Importer-Private\Clients\II\DataLoader\key.txt"/>
                <entry key="sfdc.timeoutSecs" value="600"/>
                <entry key="sfdc.loadBatchSize" value="200"/>
                <entry key="sfdc.externalIdField" value="ii_Stars_Id__c"/>
                <entry key="sfdc.entity" value="Contact"/>
                <entry key="process.operation" value="insert"/>
                <entry key="process.mappingFile" value="C:\repo\Salesforce-Importer-Private\Clients\II\Salesforce-Importer\Clients\II\DataLoader\Insert-Contact-Subs.sdl"/>
                <entry key="dataAccess.name" value="C:\repo\Salesforce-Importer-Private\Clients\II\Salesforce-Importer\Clients\II\Import\Insert-Contact-Subs.csv"/>
                <entry key="dataAccess.type" value="csvRead"/>
                <entry key="process.initialLastRunDate" value="2006-12-01T00:00:00.000-0800"/>
            </map>
        </property>
    </bean>
    <bean id="Update-Contact-Facility_Sandbox"
          class="com.salesforce.dataloader.process.ProcessRunner"
          singleton="false">
        <description>Contact Update job gets the Contact record updates from a CSV file and uploads them to salesforce using 'update'.</description>
        <property name="name" value="Update-Contact-Facility_Sandbox"/>
        <property name="configOverrideMap">
            <map>
                <entry key="sfdc.endpoint" value="https://test.salesforce.com"/> 
                <entry key="sfdc.username" value="calendar@501commons.org.master"/>
                <entry key="sfdc.password" value="c347e0598ea8455126755d47471397f251536bee9164f04783fea47428559fbabb71d46e60e6a078f86fa2d30ac340ff8e64c0ca66648917a8a949e7533de9ab"/>
                <entry key="process.encryptionKeyFile" value="C:\repo\Salesforce-Importer-Private\Clients\II\DataLoader\key.txt"/>
                <entry key="sfdc.timeoutSecs" value="600"/>
                <entry key="sfdc.loadBatchSize" value="200"/>
                <entry key="sfdc.externalIdField" value="Id"/>
                <entry key="sfdc.entity" value="Contact"/>
                <entry key="process.operation" value="update"/>
                <entry key="process.mappingFile" value="C:\repo\Salesforce-Importer-Private\Clients\II\Salesforce-Importer\Clients\II\DataLoader\Update-Contact-Facility.sdl"/>
                <entry key="dataAccess.name" value="C:\repo\Salesforce-Importer-Private\Clients\II\Salesforce-Importer\Clients\II\Import\Update-Contact-Facility.csv"/>
                <entry key="dataAccess.type" value="csvRead"/>
                <entry key="process.initialLastRunDate" value="2006-12-01T00:00:00.000-0800"/>
            </map>
        </property>
    </bean>
    <bean id="Update-Contact-Subs_Sandbox"
          class="com.salesforce.dataloader.process.ProcessRunner"
          singleton="false">
        <description>Contact Update job gets the Contact record updates from a CSV file and uploads them to salesforce using 'update'.</description>
        <property name="name" value="Update-Contact-Subs_Sandbox"/>
        <property name="configOverrideMap">
            <map>
                <entry key="sfdc.endpoint" value="https://test.salesforce.com"/> 
                <entry key="sfdc.username" value="calendar@501commons.org.master"/>
                <entry key="sfdc.password" value="c347e0598ea8455126755d47471397f251536bee9164f04783fea47428559fbabb71d46e60e6a078f86fa2d30ac340ff8e64c0ca66648917a8a949e7533de9ab"/>
                <entry key="process.encryptionKeyFile" value="C:\repo\Salesforce-Importer-Private\Clients\II\DataLoader\key.txt"/>
                <entry key="sfdc.timeoutSecs" value="600"/>
                <entry key="sfdc.loadBatchSize" value="200"/>
                <entry key="sfdc.externalIdField" value="Id"/>
                <entry key="sfdc.entity" value="Contact"/>
                <entry key="process.operation" value="update"/>
                <entry key="process.mappingFile" value="C:\repo\Salesforce-Importer-Private\Clients\II\Salesforce-Importer\Clients\II\DataLoader\Update-Contact-Subs.sdl"/>
                <entry key="dataAccess.name" value="C:\repo\Salesforce-Importer-Private\Clients\II\Salesforce-Importer\Clients\II\Import\Update-Contact-Subs.csv"/>
                <entry key="dataAccess.type" value="csvRead"/>
                <entry key="process.initialLastRunDate" value="2006-12-01T00:00:00.000-0800"/>
            </map>
        </property>
    </bean>    
    <bean id="Update-Contact-Facility-NotApp_Sandbox"
          class="com.salesforce.dataloader.process.ProcessRunner"
          singleton="false">
        <description>Contact Update job gets the Contact record updates from a CSV file and uploads them to salesforce using 'update'.</description>
        <property name="name" value="Update-Contact-Facility-NotApp_Sandbox"/>
        <property name="configOverrideMap">
            <map>
                <entry key="sfdc.endpoint" value="https://test.salesforce.com"/> 
                <entry key="sfdc.username" value="calendar@501commons.org.master"/>
                <entry key="sfdc.password" value="c347e0598ea8455126755d47471397f251536bee9164f04783fea47428559fbabb71d46e60e6a078f86fa2d30ac340ff8e64c0ca66648917a8a949e7533de9ab"/>
                <entry key="process.encryptionKeyFile" value="C:\repo\Salesforce-Importer-Private\Clients\II\DataLoader\key.txt"/>
                <entry key="sfdc.timeoutSecs" value="600"/>
                <entry key="sfdc.loadBatchSize" value="200"/>
                <entry key="sfdc.externalIdField" value="Id"/>
                <entry key="sfdc.entity" value="Contact"/>
                <entry key="process.operation" value="update"/>
                <entry key="process.mappingFile" value="C:\repo\Salesforce-Importer-Private\Clients\II\Salesforce-Importer\Clients\II\DataLoader\Update-Contact-Facility-NotApp.sdl"/>
                <entry key="dataAccess.name" value="C:\repo\Salesforce-Importer-Private\Clients\II\Salesforce-Importer\Clients\II\Import\Update-Contact-Facility-NotApp.csv"/>
                <entry key="dataAccess.type" value="csvRead"/>
                <entry key="process.initialLastRunDate" value="2006-12-01T00:00:00.000-0800"/>
            </map>
        </property>
    </bean>
    <bean id="Update-Contact-Subs-NotApp_Sandbox"
          class="com.salesforce.dataloader.process.ProcessRunner"
          singleton="false">
        <description>Contact Update job gets the Contact record updates from a CSV file and uploads them to salesforce using 'update'.</description>
        <property name="name" value="Update-Contact-Subs-NotApp_Sandbox"/>
        <property name="configOverrideMap">
            <map>
                <entry key="sfdc.endpoint" value="https://test.salesforce.com"/> 
                <entry key="sfdc.username" value="calendar@501commons.org.master"/>
                <entry key="sfdc.password" value="c347e0598ea8455126755d47471397f251536bee9164f04783fea47428559fbabb71d46e60e6a078f86fa2d30ac340ff8e64c0ca66648917a8a949e7533de9ab"/>
                <entry key="process.encryptionKeyFile" value="C:\repo\Salesforce-Importer-Private\Clients\II\DataLoader\key.txt"/>
                <entry key="sfdc.timeoutSecs" value="600"/>
                <entry key="sfdc.loadBatchSize" value="200"/>
                <entry key="sfdc.externalIdField" value="Id"/>
                <entry key="sfdc.entity" value="Contact"/>
                <entry key="process.operation" value="update"/>
                <entry key="process.mappingFile" value="C:\repo\Salesforce-Importer-Private\Clients\II\Salesforce-Importer\Clients\II\DataLoader\Update-Contact-Subs-NotApp.sdl"/>
                <entry key="dataAccess.name" value="C:\repo\Salesforce-Importer-Private\Clients\II\Salesforce-Importer\Clients\II\Import\Update-Contact-Subs-NotApp.csv"/>
                <entry key="dataAccess.type" value="csvRead"/>
                <entry key="process.initialLastRunDate" value="2006-12-01T00:00:00.000-0800"/>
            </map>
        </property>
    </bean>
    <bean id="Update-AM-Campus-User_Sandbox"
          class="com.salesforce.dataloader.process.ProcessRunner"
          singleton="false">
        <description>Contact Update job gets the Contact record updates from a CSV file and uploads them to salesforce using 'update'.</description>
        <property name="name" value="Update-AM-Campus-User_Sandbox"/>
        <property name="configOverrideMap">
            <map>
                <entry key="sfdc.endpoint" value="https://test.salesforce.com"/> 
                <entry key="sfdc.username" value="calendar@501commons.org.master"/>
                <entry key="sfdc.password" value="c347e0598ea8455126755d47471397f251536bee9164f04783fea47428559fbabb71d46e60e6a078f86fa2d30ac340ff8e64c0ca66648917a8a949e7533de9ab"/>
                <entry key="process.encryptionKeyFile" value="C:\repo\Salesforce-Importer-Private\Clients\II\DataLoader\key.txt"/>
                <entry key="sfdc.timeoutSecs" value="600"/>
                <entry key="sfdc.loadBatchSize" value="200"/>
                <entry key="sfdc.externalIdField" value="Id"/>
                <entry key="sfdc.entity" value="Contact"/>
                <entry key="process.operation" value="update"/>
                <entry key="process.mappingFile" value="C:\repo\Salesforce-Importer-Private\Clients\II\Salesforce-Importer\Clients\II\DataLoader\Update-AM-Campus-User.sdl"/>
                <entry key="dataAccess.name" value="C:\repo\Salesforce-Importer-Private\Clients\II\Salesforce-Importer\Clients\II\Import\Update-AM-Campus-User.csv"/>
                <entry key="dataAccess.type" value="csvRead"/>
                <entry key="process.initialLastRunDate" value="2006-12-01T00:00:00.000-0800"/>
            </map>
        </property>
    </bean>
    <bean id="Update-AM-Facility_Sandbox"
          class="com.salesforce.dataloader.process.ProcessRunner"
          singleton="false">
        <description>Contact Update job gets the Contact record updates from a CSV file and uploads them to salesforce using 'update'.</description>
        <property name="name" value="Update-AM-Facility_Sandbox"/>
        <property name="configOverrideMap">
            <map>
                <entry key="sfdc.endpoint" value="https://test.salesforce.com"/> 
                <entry key="sfdc.username" value="calendar@501commons.org.master"/>
                <entry key="sfdc.password" value="c347e0598ea8455126755d47471397f251536bee9164f04783fea47428559fbabb71d46e60e6a078f86fa2d30ac340ff8e64c0ca66648917a8a949e7533de9ab"/>
                <entry key="process.encryptionKeyFile" value="C:\repo\Salesforce-Importer-Private\Clients\II\DataLoader\key.txt"/>
                <entry key="sfdc.timeoutSecs" value="600"/>
                <entry key="sfdc.loadBatchSize" value="200"/>
                <entry key="sfdc.externalIdField" value="Id"/>
                <entry key="sfdc.entity" value="Contact"/>
                <entry key="process.operation" value="update"/>
                <entry key="process.mappingFile" value="C:\repo\Salesforce-Importer-Private\Clients\II\Salesforce-Importer\Clients\II\DataLoader\Update-AM-Facility.sdl"/>
                <entry key="dataAccess.name" value="C:\repo\Salesforce-Importer-Private\Clients\II\Salesforce-Importer\Clients\II\Import\Update-AM-Facility.csv"/>
                <entry key="dataAccess.type" value="csvRead"/>
                <entry key="process.initialLastRunDate" value="2006-12-01T00:00:00.000-0800"/>
            </map>
        </property>
    </bean>
    <bean id="Update-AM-Subs_Sandbox"
          class="com.salesforce.dataloader.process.ProcessRunner"
          singleton="false">
        <description>Contact Update job gets the Contact record updates from a CSV file and uploads them to salesforce using 'update'.</description>
        <property name="name" value="Update-AM-Subs_Sandbox"/>
        <property name="configOverrideMap">
            <map>
                <entry key="sfdc.endpoint" value="https://test.salesforce.com"/> 
                <entry key="sfdc.username" value="calendar@501commons.org.master"/>
                <entry key="sfdc.password" value="c347e0598ea8455126755d47471397f251536bee9164f04783fea47428559fbabb71d46e60e6a078f86fa2d30ac340ff8e64c0ca66648917a8a949e7533de9ab"/>
                <entry key="process.encryptionKeyFile" value="C:\repo\Salesforce-Importer-Private\Clients\II\DataLoader\key.txt"/>
                <entry key="sfdc.timeoutSecs" value="600"/>
                <entry key="sfdc.loadBatchSize" value="200"/>
                <entry key="sfdc.externalIdField" value="Id"/>
                <entry key="sfdc.entity" value="Contact"/>
                <entry key="process.operation" value="update"/>
                <entry key="process.mappingFile" value="C:\repo\Salesforce-Importer-Private\Clients\II\Salesforce-Importer\Clients\II\DataLoader\Update-AM-Subs.sdl"/>
                <entry key="dataAccess.name" value="C:\repo\Salesforce-Importer-Private\Clients\II\Salesforce-Importer\Clients\II\Import\Update-AM-Subs.csv"/>
                <entry key="dataAccess.type" value="csvRead"/>
                <entry key="process.initialLastRunDate" value="2006-12-01T00:00:00.000-0800"/>
            </map>
        </property>
    </bean>
    <bean id="Insert-Contact-Training_Sandbox"
          class="com.salesforce.dataloader.process.ProcessRunner"
          singleton="false">
        <description>Contact Insert job gets the Contact record updates from a CSV file and uploads them to salesforce using 'insert'.</description>
        <property name="name" value="Insert-Contact-Training_Sandbox"/>
        <property name="configOverrideMap">
            <map>
                <entry key="sfdc.endpoint" value="https://test.salesforce.com"/> 
                <entry key="sfdc.username" value="calendar@501commons.org.master"/>
                <entry key="sfdc.password" value="c347e0598ea8455126755d47471397f251536bee9164f04783fea47428559fbabb71d46e60e6a078f86fa2d30ac340ff8e64c0ca66648917a8a949e7533de9ab"/>
                <entry key="process.encryptionKeyFile" value="C:\repo\Salesforce-Importer-Private\Clients\II\DataLoader\key.txt"/>
                <entry key="sfdc.timeoutSecs" value="600"/>
                <entry key="sfdc.loadBatchSize" value="200"/>
                <entry key="sfdc.externalIdField" value="ii_Member_Id__c"/>
                <entry key="sfdc.entity" value="Contact"/>
                <entry key="process.operation" value="insert"/>
                <entry key="process.mappingFile" value="C:\repo\Salesforce-Importer-Private\Clients\II\Salesforce-Importer\Clients\II\DataLoader\Insert-Contact-Training.sdl"/>
                <entry key="dataAccess.name" value="C:\repo\Salesforce-Importer-Private\Clients\II\Salesforce-Importer\Clients\II\Import\Insert-Contact-Training.csv"/>
                <entry key="dataAccess.type" value="csvRead"/>
                <entry key="process.initialLastRunDate" value="2006-12-01T00:00:00.000-0800"/>
            </map>
        </property>
    </bean>
    <bean id="Update-Contact-Training_Sandbox"
          class="com.salesforce.dataloader.process.ProcessRunner"
          singleton="false">
        <description>Contact Update job gets the Contact record updates from a CSV file and uploads them to salesforce using 'update'.</description>
        <property name="name" value="Update-Contact-Training_Sandbox"/>
        <property name="configOverrideMap">
            <map>
                <entry key="sfdc.endpoint" value="https://test.salesforce.com"/> 
                <entry key="sfdc.username" value="calendar@501commons.org.master"/>
                <entry key="sfdc.password" value="c347e0598ea8455126755d47471397f251536bee9164f04783fea47428559fbabb71d46e60e6a078f86fa2d30ac340ff8e64c0ca66648917a8a949e7533de9ab"/>
                <entry key="process.encryptionKeyFile" value="C:\repo\Salesforce-Importer-Private\Clients\II\DataLoader\key.txt"/>
                <entry key="sfdc.timeoutSecs" value="600"/>
                <entry key="sfdc.loadBatchSize" value="200"/>
                <entry key="sfdc.externalIdField" value="Id"/>
                <entry key="sfdc.entity" value="Contact"/>
                <entry key="process.operation" value="update"/>
                <entry key="process.mappingFile" value="C:\repo\Salesforce-Importer-Private\Clients\II\Salesforce-Importer\Clients\II\DataLoader\Update-Contact-Training.sdl"/>
                <entry key="dataAccess.name" value="C:\repo\Salesforce-Importer-Private\Clients\II\Salesforce-Importer\Clients\II\Import\Update-Contact-Training.csv"/>
                <entry key="dataAccess.type" value="csvRead"/>
                <entry key="process.initialLastRunDate" value="2006-12-01T00:00:00.000-0800"/>
            </map>
        </property>
    </bean>
    <bean id="Update-Training-OutOfUnit_Sandbox"
          class="com.salesforce.dataloader.process.ProcessRunner"
          singleton="false">
        <description>Contact Update job gets the Contact record updates from a CSV file and uploads them to salesforce using 'update'.</description>
        <property name="name" value="Update-Traininig-OutOfUnit_Sandbox"/>
        <property name="configOverrideMap">
            <map>
                <entry key="sfdc.endpoint" value="https://test.salesforce.com"/> 
                <entry key="sfdc.username" value="calendar@501commons.org.master"/>
                <entry key="sfdc.password" value="c347e0598ea8455126755d47471397f251536bee9164f04783fea47428559fbabb71d46e60e6a078f86fa2d30ac340ff8e64c0ca66648917a8a949e7533de9ab"/>
                <entry key="process.encryptionKeyFile" value="C:\repo\Salesforce-Importer-Private\Clients\II\DataLoader\key.txt"/>
                <entry key="sfdc.timeoutSecs" value="600"/>
                <entry key="sfdc.loadBatchSize" value="200"/>
                <entry key="sfdc.externalIdField" value="Id"/>
                <entry key="sfdc.entity" value="Contact"/>
                <entry key="process.operation" value="update"/>
                <entry key="process.mappingFile" value="C:\repo\Salesforce-Importer-Private\Clients\II\Salesforce-Importer\Clients\II\DataLoader\Update-Training-OutOfUnit.sdl"/>
                <entry key="dataAccess.name" value="C:\repo\Salesforce-Importer-Private\Clients\II\Salesforce-Importer\Clients\II\Import\Update-Training-OutOfUnit.csv"/>
                <entry key="dataAccess.type" value="csvRead"/>
                <entry key="process.initialLastRunDate" value="2006-12-01T00:00:00.000-0800"/>
            </map>
        </property>
    </bean>
    <bean id="Insert-Contact-FFN_Prod"
          class="com.salesforce.dataloader.process.ProcessRunner"
          singleton="false">
        <description>Contact Insert job gets the Contact record updates from a CSV file and uploads them to salesforce using 'insert'.</description>
        <property name="name" value="Insert-Contact-FFN_Prod"/>
        <property name="configOverrideMap">
            <map>
                <entry key="sfdc.endpoint" value="https://imagineinstitute.my.salesforce.com"/> 
                <entry key="sfdc.username" value="calendar@501commons.org"/>
                <entry key="sfdc.password" value="41c54d6703a9a7e3ff5e10bdd8498552d9ac6476aae41e2b21c5d99229c554f33b25768df3adbdf7c6e1da27527fa4d791d6ec21f60b6bf8a0fa9c731d1c5080"/>
                <entry key="process.encryptionKeyFile" value="C:\repo\Salesforce-Importer-Private\Clients\II\DataLoader\key.txt"/>
                <entry key="sfdc.timeoutSecs" value="600"/>
                <entry key="sfdc.loadBatchSize" value="200"/>
                <entry key="sfdc.externalIdField" value="ii_Member_Id__c"/>
                <entry key="sfdc.entity" value="Contact"/>
                <entry key="process.operation" value="insert"/>
                <entry key="process.mappingFile" value="C:\repo\Salesforce-Importer-Private\Clients\II\Salesforce-Importer\Clients\II\DataLoader\Insert-Contact-FFN.sdl"/>
                <entry key="dataAccess.name" value="C:\repo\Salesforce-Importer-Private\Clients\II\Salesforce-Importer\Clients\II\Import\Insert-Contact-FFN.csv"/>
                <entry key="dataAccess.type" value="csvRead"/>
                <entry key="process.initialLastRunDate" value="2006-12-01T00:00:00.000-0800"/>
            </map>
        </property>
    </bean>
    <bean id="Update-Contact-FFN_Prod"
          class="com.salesforce.dataloader.process.ProcessRunner"
          singleton="false">
        <description>Contact Update job gets the Contact record updates from a CSV file and uploads them to salesforce using 'update'.</description>
        <property name="name" value="Update-Contact-FFN_Prod"/>
        <property name="configOverrideMap">
            <map>
                <entry key="sfdc.endpoint" value="https://imagineinstitute.my.salesforce.com"/> 
                <entry key="sfdc.username" value="calendar@501commons.org"/>
                <entry key="sfdc.password" value="41c54d6703a9a7e3ff5e10bdd8498552d9ac6476aae41e2b21c5d99229c554f33b25768df3adbdf7c6e1da27527fa4d791d6ec21f60b6bf8a0fa9c731d1c5080"/>
                <entry key="process.encryptionKeyFile" value="C:\repo\Salesforce-Importer-Private\Clients\II\DataLoader\key.txt"/>
                <entry key="sfdc.timeoutSecs" value="600"/>
                <entry key="sfdc.loadBatchSize" value="200"/>
                <entry key="sfdc.externalIdField" value="Id"/>
                <entry key="sfdc.entity" value="Contact"/>
                <entry key="process.operation" value="update"/>
                <entry key="process.mappingFile" value="C:\repo\Salesforce-Importer-Private\Clients\II\Salesforce-Importer\Clients\II\DataLoader\Update-Contact-FFN.sdl"/>
                <entry key="dataAccess.name" value="C:\repo\Salesforce-Importer-Private\Clients\II\Salesforce-Importer\Clients\II\Import\Update-Contact-FFN.csv"/>
                <entry key="dataAccess.type" value="csvRead"/>
                <entry key="process.initialLastRunDate" value="2006-12-01T00:00:00.000-0800"/>
            </map>
        </property>
    </bean>
    <bean id="Update-Contact-StarsId-FFN_Prod"
          class="com.salesforce.dataloader.process.ProcessRunner"
          singleton="false">
        <description>Contact Update job gets the Contact record updates from a CSV file and uploads them to salesforce using 'update'.</description>
        <property name="name" value="Update-Contact-StarsId-FFN_Prod"/>
        <property name="configOverrideMap">
            <map>
                <entry key="sfdc.endpoint" value="https://imagineinstitute.my.salesforce.com"/> 
                <entry key="sfdc.username" value="calendar@501commons.org"/>
                <entry key="sfdc.password" value="41c54d6703a9a7e3ff5e10bdd8498552d9ac6476aae41e2b21c5d99229c554f33b25768df3adbdf7c6e1da27527fa4d791d6ec21f60b6bf8a0fa9c731d1c5080"/>
                <entry key="process.encryptionKeyFile" value="C:\repo\Salesforce-Importer-Private\Clients\II\DataLoader\key.txt"/>
                <entry key="sfdc.timeoutSecs" value="600"/>
                <entry key="sfdc.loadBatchSize" value="200"/>
                <entry key="sfdc.externalIdField" value="Id"/>
                <entry key="sfdc.entity" value="Contact"/>
                <entry key="process.operation" value="update"/>
                <entry key="process.mappingFile" value="C:\repo\Salesforce-Importer-Private\Clients\II\Salesforce-Importer\Clients\II\DataLoader\Update-Contact-StarsId-FFN.sdl"/>
                <entry key="dataAccess.name" value="C:\repo\Salesforce-Importer-Private\Clients\II\Salesforce-Importer\Clients\II\Import\Update-Contact-StarsId-FFN.csv"/>
                <entry key="dataAccess.type" value="csvRead"/>
                <entry key="process.initialLastRunDate" value="2006-12-01T00:00:00.000-0800"/>
            </map>
        </property>
    </bean>
    <bean id="Update-Contact-FFN-OutOfUnit_Prod"
          class="com.salesforce.dataloader.process.ProcessRunner"
          singleton="false">
        <description>Contact Update job gets the Contact record updates from a CSV file and uploads them to salesforce using 'update'.</description>
        <property name="name" value="Update-Contact-FFN_Prod"/>
        <property name="configOverrideMap">
            <map>
                <entry key="sfdc.endpoint" value="https://imagineinstitute.my.salesforce.com"/> 
                <entry key="sfdc.username" value="calendar@501commons.org"/>
                <entry key="sfdc.password" value="41c54d6703a9a7e3ff5e10bdd8498552d9ac6476aae41e2b21c5d99229c554f33b25768df3adbdf7c6e1da27527fa4d791d6ec21f60b6bf8a0fa9c731d1c5080"/>
                <entry key="process.encryptionKeyFile" value="C:\repo\Salesforce-Importer-Private\Clients\II\DataLoader\key.txt"/>
                <entry key="sfdc.timeoutSecs" value="600"/>
                <entry key="sfdc.loadBatchSize" value="200"/>
                <entry key="sfdc.externalIdField" value="Id"/>
                <entry key="sfdc.entity" value="Contact"/>
                <entry key="process.operation" value="update"/>
                <entry key="process.mappingFile" value="C:\repo\Salesforce-Importer-Private\Clients\II\Salesforce-Importer\Clients\II\DataLoader\Update-Contact-FFN-OutOfUnit.sdl"/>
                <entry key="dataAccess.name" value="C:\repo\Salesforce-Importer-Private\Clients\II\Salesforce-Importer\Clients\II\Import\Update-Contact-FFN-OutOfUnit.csv"/>
                <entry key="dataAccess.type" value="csvRead"/>
                <entry key="process.initialLastRunDate" value="2006-12-01T00:00:00.000-0800"/>
            </map>
        </property>
    </bean>
    <bean id="Insert-Contact-FFN_Sandbox"
          class="com.salesforce.dataloader.process.ProcessRunner"
          singleton="false">
        <description>Contact Insert job gets the Contact record updates from a CSV file and uploads them to salesforce using 'insert'.</description>
        <property name="name" value="Insert-Contact-FFN_Sandbox"/>
        <property name="configOverrideMap">
            <map>
                <entry key="sfdc.endpoint" value="https://test.salesforce.com"/> 
                <entry key="sfdc.username" value="calendar@501commons.org.master"/>
                <entry key="sfdc.password" value="c347e0598ea8455126755d47471397f251536bee9164f04783fea47428559fbabb71d46e60e6a078f86fa2d30ac340ff8e64c0ca66648917a8a949e7533de9ab"/>
                <entry key="process.encryptionKeyFile" value="C:\repo\Salesforce-Importer-Private\Clients\II\DataLoader\key.txt"/>
                <entry key="sfdc.timeoutSecs" value="600"/>
                <entry key="sfdc.loadBatchSize" value="200"/>
                <entry key="sfdc.externalIdField" value="ii_Member_Id__c"/>
                <entry key="sfdc.entity" value="Contact"/>
                <entry key="process.operation" value="insert"/>
                <entry key="process.mappingFile" value="C:\repo\Salesforce-Importer-Private\Clients\II\Salesforce-Importer\Clients\II\DataLoader\Insert-Contact-FFN.sdl"/>
                <entry key="dataAccess.name" value="C:\repo\Salesforce-Importer-Private\Clients\II\Salesforce-Importer\Clients\II\Import\Insert-Contact-FFN.csv"/>
                <entry key="dataAccess.type" value="csvRead"/>
                <entry key="process.initialLastRunDate" value="2006-12-01T00:00:00.000-0800"/>
            </map>
        </property>
    </bean>
    <bean id="Update-Contact-FFN_Sandbox"
          class="com.salesforce.dataloader.process.ProcessRunner"
          singleton="false">
        <description>Contact Update job gets the Contact record updates from a CSV file and uploads them to salesforce using 'update'.</description>
        <property name="name" value="Update-Contact-FFN_Sandbox"/>
        <property name="configOverrideMap">
            <map>
                <entry key="sfdc.endpoint" value="https://test.salesforce.com"/> 
                <entry key="sfdc.username" value="calendar@501commons.org.master"/>
                <entry key="sfdc.password" value="c347e0598ea8455126755d47471397f251536bee9164f04783fea47428559fbabb71d46e60e6a078f86fa2d30ac340ff8e64c0ca66648917a8a949e7533de9ab"/>
                <entry key="process.encryptionKeyFile" value="C:\repo\Salesforce-Importer-Private\Clients\II\DataLoader\key.txt"/>
                <entry key="sfdc.timeoutSecs" value="600"/>
                <entry key="sfdc.loadBatchSize" value="200"/>
                <entry key="sfdc.externalIdField" value="Id"/>
                <entry key="sfdc.entity" value="Contact"/>
                <entry key="process.operation" value="update"/>
                <entry key="process.mappingFile" value="C:\repo\Salesforce-Importer-Private\Clients\II\Salesforce-Importer\Clients\II\DataLoader\Update-Contact-FFN.sdl"/>
                <entry key="dataAccess.name" value="C:\repo\Salesforce-Importer-Private\Clients\II\Salesforce-Importer\Clients\II\Import\Update-Contact-FFN.csv"/>
                <entry key="dataAccess.type" value="csvRead"/>
                <entry key="process.initialLastRunDate" value="2006-12-01T00:00:00.000-0800"/>
            </map>
        </property>
    </bean>
    <bean id="Update-Contact-FFN-OutOfUnit_Sandbox"
          class="com.salesforce.dataloader.process.ProcessRunner"
          singleton="false">
        <description>Contact Update job gets the Contact record updates from a CSV file and uploads them to salesforce using 'update'.</description>
        <property name="name" value="Update-Contact-FFN_Sandbox"/>
        <property name="configOverrideMap">
            <map>
                <entry key="sfdc.endpoint" value="https://test.salesforce.com"/> 
                <entry key="sfdc.username" value="calendar@501commons.org.master"/>
                <entry key="sfdc.password" value="c347e0598ea8455126755d47471397f251536bee9164f04783fea47428559fbabb71d46e60e6a078f86fa2d30ac340ff8e64c0ca66648917a8a949e7533de9ab"/>
                <entry key="process.encryptionKeyFile" value="C:\repo\Salesforce-Importer-Private\Clients\II\DataLoader\key.txt"/>
                <entry key="sfdc.timeoutSecs" value="600"/>
                <entry key="sfdc.loadBatchSize" value="200"/>
                <entry key="sfdc.externalIdField" value="Id"/>
                <entry key="sfdc.entity" value="Contact"/>
                <entry key="process.operation" value="update"/>
                <entry key="process.mappingFile" value="C:\repo\Salesforce-Importer-Private\Clients\II\Salesforce-Importer\Clients\II\DataLoader\Update-Contact-FFN-OutOfUnit.sdl"/>
                <entry key="dataAccess.name" value="C:\repo\Salesforce-Importer-Private\Clients\II\Salesforce-Importer\Clients\II\Import\Update-Contact-FFN-OutOfUnit.csv"/>
                <entry key="dataAccess.type" value="csvRead"/>
                <entry key="process.initialLastRunDate" value="2006-12-01T00:00:00.000-0800"/>
            </map>
        </property>
    </bean>
</beans>
